CHANGES.rst
LICENSE.txt
MANIFEST.in
README.rst
setup.py
src/bst/__init__.py
src/bst.pygasus.datamanager.egg-info/PKG-INFO
src/bst.pygasus.datamanager.egg-info/SOURCES.txt
src/bst.pygasus.datamanager.egg-info/dependency_links.txt
src/bst.pygasus.datamanager.egg-info/namespace_packages.txt
src/bst.pygasus.datamanager.egg-info/not-zip-safe
src/bst.pygasus.datamanager.egg-info/requires.txt
src/bst.pygasus.datamanager.egg-info/top_level.txt
src/bst/pygasus/__init__.py
src/bst/pygasus/datamanager/__init__.py
src/bst/pygasus/datamanager/configure.zcml
src/bst/pygasus/datamanager/datamanager.py
src/bst/pygasus/datamanager/errorhandling.py
src/bst/pygasus/datamanager/grokker.py
src/bst/pygasus/datamanager/interfaces.py
src/bst/pygasus/datamanager/model.py
src/bst/pygasus/datamanager/transformer.py